{
  "profile_image_url": "https://i.ibb.co/spRvKYkd/cec6af7b3601.jpg",
  "name": "LEE TAE HAN",
  "desc": "",
  "bg_color": "#ffffff",
  "btn_color": "#631dfc",
  "btn_radius": 8,
  "btn_effect": "float",
  "btn_gradient": true,
  "btn_color2": "#20bdff",
  "links": [
    {
      "id": "1779167558107",
      "title": "홈페이지 바로가기",
      "url": "http://metaplace.co.kr"
    },
    {
      "id": "1779171221171",
      "title": "카톡문의 바로가기",
      "url": "http://pf.kakao.com/_xjPQxgn/chat"
    }
  ]
}